Metadata-Version: 1.0
Name: krantsonemailgo
Version: 0.3
Summary: A email client in termial
Home-page: http://www.163.com
Author: Xing Wan
Author-email: krantson@163.com
License: UNKNOWN
Platform: UNKNOWN
